{
  "book": "Psalms",
  "chapter": 108,
  "verses": [
    {
      "number": 1,
      "ko": "하나님이여 내 마음을 정하였사오니 내가 노래하며 나의 마음을 다하여 찬양하리로다",
      "en": "A song. A psalm of David. My heart is steadfast, O God; I will sing and make music with all my soul.",
      "de": "Ein Psalmlied Davids. Gott, es ist mein rechter Ernst; ich will singen und dichten, meine Ehre auch.",
      "zh": "大卫的诗歌。 　神啊，我心坚定； 我口要唱诗歌颂！",
      "ja": "神よわが心はさだまれり われ謳ひまつらん 稱まつらん わが榮をもてたたへまつらん"
    },
    {
      "number": 2,
      "ko": "비파야, 수금아, 깰지어다 내가 새벽을 깨우리로다",
      "en": "Awake, harp and lyre! I will awaken the dawn.",
      "de": "Wohlauf, Psalter und Harfe! Ich will in der Frühe auf sein.",
      "zh": "琴瑟啊，你们当醒起！ 我自己要极早醒起！",
      "ja": "筝よ琴よさむべし われ黎明をよびさまさん"
    },
    {
      "number": 3,
      "ko": "여호와여 내가 만민 중에서 주께 감사하고 뭇 나라 중에서 주를 찬양하오리니",
      "en": "I will praise you, O LORD, among the nations; I will sing of you among the peoples.",
      "de": "Ich will dir danken, HERR, unter den Völkern; ich will dir lobsingen unter den Leuten.",
      "zh": "耶和华啊，我要在万民中称谢你， 在列邦中歌颂你！",
      "ja": "ヱホバよ我もろもろの民のなかにてなんぢに感謝し もろもろの國のなかにてなんぢをほめうたはん"
    },
    {
      "number": 4,
      "ko": "주의 인자하심이 하늘보다 높으시며 주의 진실은 궁창에까지 이르나이다",
      "en": "For great is your love, higher than the heavens; your faithfulness reaches to the skies.",
      "de": "Denn deine Gnade reicht, soweit der Himmel ist, und deine Wahrheit, soweit die Wolken gehen.",
      "zh": "因为，你的慈爱大过诸天； 你的诚实达到穹苍。",
      "ja": "そは汝のあはれみは大にして天のうへにあがり なんぢの眞實は雲にまでおよぶ"
    },
    {
      "number": 5,
      "ko": "하나님이여 주는 하늘 위에 높이 들리시며 주의 영광이 온 땅에서 높임 받으시기를 원하나이다",
      "en": "Be exalted, O God, above the heavens, and let your glory be over all the earth.",
      "de": "Erhebe dich, Gott, über den Himmel, und deine Ehre über alle Lande.",
      "zh": "神啊，愿你崇高过于诸天！ 愿你的荣耀高过全地！",
      "ja": "神よねがはくはみづからを天よりもたかくし榮光を全地のうへに擧たまへ"
    },
    {
      "number": 6,
      "ko": "주께서 사랑하시는 자들을 건지시기 위하여 우리에게 응답하사 오른손으로 구원하소서",
      "en": "Save us and help us with your right hand, that those you love may be delivered.",
      "de": "Auf daß deine lieben Freunde erledigt werden, hilf mit deiner Rechten und erhöre mich!",
      "zh": "求你应允我们，用右手拯救我们， 好叫你所亲爱的人得救。",
      "ja": "ねがはくは右の手をもて救をほどこし われらに答をなして愛しみたまふものに助をえしめたまへ"
    },
    {
      "number": 7,
      "ko": "하나님이 그의 성소에서 말씀하시되 내가 기뻐하리라 내가 세겜을 나누며 숙곳 골짜기를 측량하리라",
      "en": "God has spoken from his sanctuary: \"In triumph I will parcel out Shechem and measure off the Valley of Succoth.",
      "de": "Gott redete in seinem Heiligtum, des bin ich froh, und will Sichem teilen und das Tal Sukkoth abmessen.",
      "zh": "神已经指着他的圣洁说： 我要欢乐；我要分开示剑， 丈量疏割谷。",
      "ja": "神はその聖をもていひたまへり われ甚くよろこばん我シケムをわかちスコテの谷をはからん"
    },
    {
      "number": 8,
      "ko": "길르앗이 내 것이요 므낫세도 내 것이며 에브라임은 내 머리의 투구요 유다는 나의 규이며",
      "en": "Gilead is mine, Manasseh is mine; Ephraim is my helmet, Judah my scepter.",
      "de": "Gilead ist mein, Manasse ist auch mein, und Ephraim ist die Macht meines Hauptes, Juda ist mein Zepter,",
      "zh": "基列是我的； 玛拿西是我的； 以法莲是护卫我头的； 犹大是我的杖；",
      "ja": "ギレアデはわがものマナセはわが有なりエフライムも亦わが首のまもりなりユダはわが杖"
    },
    {
      "number": 9,
      "ko": "모압은 내 목욕통이라 에돔에는 내 신발을 벗어 던질지며 블레셋 위에서 내가 외치리라 하셨도다",
      "en": "Moab is my washbasin, upon Edom I toss my sandal; over Philistia I shout in triumph.\"",
      "de": "Moab ist mein Waschbecken, ich will meinen Schuh über Edom strecken, über die Philister will ich jauchzen.",
      "zh": "摩押是我的沐浴盆； 我要向以东抛鞋； 我必因胜非利士呼喊。",
      "ja": "モアブはわが足盥なりエドムにはわが履をなげんペリシテよわが故によりて聲をあげよと"
    },
    {
      "number": 10,
      "ko": "누가 나를 이끌어 견고한 성읍으로 인도해 들이며 누가 나를 에돔으로 인도할꼬",
      "en": "Who will bring me to the fortified city? Who will lead me to Edom?",
      "de": "Wer will mich führen in eine feste Stadt? Wer wird mich leiten bis nach Edom?",
      "zh": "谁能领我进坚固城？ 谁能引我到以东地？",
      "ja": "誰かわれを堅固なる邑にすすましめんや 誰かわれをみちびきてエドムにゆきしや"
    },
    {
      "number": 11,
      "ko": "하나님이여 주께서 우리를 버리지 아니하셨나이까 하나님이여 주께서 우리의 군대들과 함께 나아가지 아니하시나이다",
      "en": "Is it not you, O God, you who have rejected us and no longer go out with our armies?",
      "de": "Wirst du es nicht tun, Gott, der du uns verstößest und ziehest nicht aus, Gott, mit unserm Heer?",
      "zh": "神啊，你不是丢弃了我们吗？ 　神啊，你不和我们的军兵同去吗？",
      "ja": "神よなんぢはわれらを棄たまひしにあらずや 神よなんぢはわれらの軍とともに出ゆきたまはず"
    },
    {
      "number": 12,
      "ko": "우리를 도와 대적을 치게 하소서 사람의 구원은 헛됨이니이다",
      "en": "Give us aid against the enemy, for the help of man is worthless.",
      "de": "Schaffe uns Beistand in der Not; denn Menschenhilfe ist nichts nütze.",
      "zh": "求你帮助我们攻击敌人， 因为人的帮助是枉然的。",
      "ja": "ねがはくは助をわれにあたへて敵にむかはしめたまへ 人のたすけは空しければなり"
    },
    {
      "number": 13,
      "ko": "우리가 하나님을 의지하고 용감히 행하리니 그는 우리의 대적들을 밟으실 자이심이로다",
      "en": "With God we will gain the victory, and he will trample down our enemies.",
      "de": "Mit Gott wollen wir Taten tun; er wird unsre Feinde untertreten.",
      "zh": "我们倚靠　神才得施展大能， 因为践踏我们敌人的就是他。",
      "ja": "われらは神によりて勇しくはたらかん われらの敵をふみたまふものは神なればなり"
    }
  ]
}
